Metadata-Version: 2.4
Name: marlo-mcp
Version: 0.1.19
Summary: Marlo MCP server for voyage management system for shipping companies
Project-URL: Homepage, https://www.marlo.co/
Project-URL: Repository, https://github.com/core-marlo/marlo-mcp.git
Project-URL: Documentation, https://github.com/core-marlo/marlo-mcp#readme
Project-URL: Changelog, https://github.com/core-marlo/marlo-mcp/blob/main/CHANGELOG.md
Author-email: Mathan Karthik <mka@marlo.online>
License: MIT License
License-File: LICENSE
Keywords: api,async,client,maritime,marlo,mcp,voyage management
Classifier: Development Status :: 4 - Beta
Classifier: Intended Audience :: Developers
Classifier: License :: OSI Approved :: MIT License
Classifier: Operating System :: OS Independent
Classifier: Programming Language :: Python :: 3
Classifier: Programming Language :: Python :: 3.10
Classifier: Programming Language :: Python :: 3.11
Classifier: Programming Language :: Python :: 3.12
Classifier: Programming Language :: Python :: 3.13
Classifier: Topic :: Software Development :: Libraries :: Python Modules
Requires-Python: >=3.12
Requires-Dist: httpx>=0.28.1
Requires-Dist: mcp[cli]>=1.10.1
Requires-Dist: pydantic>=2.0.0
Requires-Dist: python-dateutil>=2.8.2
Provides-Extra: dev
Requires-Dist: black>=24.0.0; extra == 'dev'
Requires-Dist: build>=1.2.2.post1; extra == 'dev'
Requires-Dist: mypy>=1.8.0; extra == 'dev'
Requires-Dist: pytest-asyncio>=0.21.0; extra == 'dev'
Requires-Dist: pytest>=7.0.0; extra == 'dev'
Requires-Dist: ruff>=0.4.0; extra == 'dev'
Requires-Dist: twine>=6.1.0; extra == 'dev'
Provides-Extra: docs
Requires-Dist: mkdocs-material>=9.5.10; extra == 'docs'
Requires-Dist: mkdocs>=1.5.3; extra == 'docs'
